LICENSE
MANIFEST.in
README
setup.py
django_helper.egg-info/PKG-INFO
django_helper.egg-info/SOURCES.txt
django_helper.egg-info/dependency_links.txt
django_helper.egg-info/not-zip-safe
django_helper.egg-info/top_level.txt
djangohelper/__init__.py
djangohelper/context_processors.py
djangohelper/decorators.py
djangohelper/helper.py
djangohelper/models.py
djangohelper/tests.py
djangohelper/views.py
djangohelper/templatetags/__init__.py
djangohelper/templatetags/djangohelper_tags.py
djangohelper/templatetags/verbatim_templatetag.py