Metadata-Version: 1.1
Name: django-helper
Version: 0.8.3
Summary: A set of useful function/tags/filter for Django.
Home-page: https://github.com/vicalloy/django-helper/
Author: vicalloy
Author-email: zbirder@gmail.com
License: BSD
Keywords: helper,django
Platform: UNKNOWN
Classifier: Programming Language :: Python
Classifier: Topic :: Software Development :: Libraries :: Python Modules
Classifier: Framework :: Django
Classifier: Environment :: Web Environment
